snapshot_dbg_cli/__init__.py
snapshot_dbg_cli/__main__.py
snapshot_dbg_cli/breakpoint_utils.py
snapshot_dbg_cli/cli.py
snapshot_dbg_cli/cli_common_arguments.py
snapshot_dbg_cli/cli_run.py
snapshot_dbg_cli/cli_services.py
snapshot_dbg_cli/cli_version.py
snapshot_dbg_cli/data_formatter.py
snapshot_dbg_cli/debuggee_utils.py
snapshot_dbg_cli/delete_breakpoints.py
snapshot_dbg_cli/delete_debuggees_command.py
snapshot_dbg_cli/delete_logpoints_command.py
snapshot_dbg_cli/delete_snapshots_command.py
snapshot_dbg_cli/exceptions.py
snapshot_dbg_cli/firebase_management_rest_service.py
snapshot_dbg_cli/firebase_rtdb_rest_service.py
snapshot_dbg_cli/firebase_types.py
snapshot_dbg_cli/gcloud_cli_service.py
snapshot_dbg_cli/get_logpoint_command.py
snapshot_dbg_cli/get_snapshot_command.py
snapshot_dbg_cli/http_service.py
snapshot_dbg_cli/init_command.py
snapshot_dbg_cli/list_debuggees_command.py
snapshot_dbg_cli/list_logpoints_command.py
snapshot_dbg_cli/list_snapshots_command.py
snapshot_dbg_cli/permissions_rest_service.py
snapshot_dbg_cli/set_logpoint_command.py
snapshot_dbg_cli/set_snapshot_command.py
snapshot_dbg_cli/snapshot_debugger_rtdb_service.py
snapshot_dbg_cli/snapshot_debugger_schema.py
snapshot_dbg_cli/snapshot_parser.py
snapshot_dbg_cli/status_message.py
snapshot_dbg_cli/time_utils.py
snapshot_dbg_cli/user_input.py
snapshot_dbg_cli/user_output.py
snapshot_dbg_cli-0.3.8.dist-info/LICENSE
snapshot_dbg_cli-0.3.8.dist-info/METADATA
snapshot_dbg_cli-0.3.8.dist-info/WHEEL
snapshot_dbg_cli-0.3.8.dist-info/entry_points.txt
snapshot_dbg_cli-0.3.8.dist-info/top_level.txt
snapshot_dbg_cli-0.3.8.dist-info/RECORD
