Metadata-Version: 2.1
Name: snapshot-dbg-cli
Version: 0.3.8
Summary: 'Snapshot Debugger CLI tool.'
Home-page: https://github.com/GoogleCloudPlatform/snapshot-debugger
Author: Google Inc.
License: Apache License, Version 2.0
Project-URL: CLI Source, https://github.com/GoogleCloudPlatform/snapshot-debugger
Project-URL: Java Agent Source, https://github.com/GoogleCloudPlatform/cloud-debug-java
Project-URL: Node.js Agent Source, https://github.com/googleapis/cloud-debug-nodejs
Project-URL: Python Agent Source, https://github.com/GoogleCloudPlatform/cloud-debug-python
Keywords: cloud,snapshot,debugger
Classifier: Development Status :: 4 - Beta
Classifier: Intended Audience :: Developers
Classifier: Programming Language :: Python
Classifier: Programming Language :: Python :: 3
Classifier: Programming Language :: Python :: 3.6
Classifier: Programming Language :: Python :: 3.7
Classifier: Programming Language :: Python :: 3.8
Classifier: Programming Language :: Python :: 3.9
Classifier: Programming Language :: Python :: 3.10
Classifier: Topic :: Software Development :: Debuggers
License-File: LICENSE
